fore_cloudreach/__init__.py
fore_cloudreach/auth.py
fore_cloudreach/errors.py
fore_cloudreach/ingester.py
fore_cloudreach/template.py
test/__init__.py
test/test_fore_cloudreach.py
fore_cloudreach-0.0.4.dev19.dist-info/LICENSE
fore_cloudreach-0.0.4.dev19.dist-info/METADATA
fore_cloudreach-0.0.4.dev19.dist-info/WHEEL
fore_cloudreach-0.0.4.dev19.dist-info/top_level.txt
fore_cloudreach-0.0.4.dev19.dist-info/RECORD
