Metadata-Version: 2.1
Name: fore-cloudreach
Version: 0.0.4.dev19
Summary: package to ingest data in Google Sheets file for FinOps reporting
Author-email: Cloudreach <nikolay.tonev@cloudreach.com>
Project-URL: Homepage, https://github.com/cloudreach/finops-reporter/browse
Project-URL: Bug Tracker, https://github.com/cloudreach/finops-reporter/issues
Classifier: Programming Language :: Python :: 3
Classifier: License :: Other/Proprietary License
Classifier: Operating System :: OS Independent
Classifier: Environment :: MacOS X
Classifier: Development Status :: 2 - Pre-Alpha
Requires-Python: >=3.7
License-File: LICENSE
Requires-Dist: google-api-python-client
Requires-Dist: google-auth-httplib2
Requires-Dist: google-auth-oauthlib
Requires-Dist: flask
Requires-Dist: requests
Requires-Dist: pathlib
Requires-Dist: pandas
Requires-Dist: boto3
